django_model_observer/__init__.py
django_model_observer/observer.py
django_model_observer/utils.py
django_model_observer-1.1.0.dist-info/LICENSE
django_model_observer-1.1.0.dist-info/METADATA
django_model_observer-1.1.0.dist-info/WHEEL
django_model_observer-1.1.0.dist-info/dependency_links.txt
django_model_observer-1.1.0.dist-info/top_level.txt
django_model_observer-1.1.0.dist-info/RECORD
